keepluggable/__init__.py
keepluggable/actions.py
keepluggable/exceptions.py
keepluggable/image_actions.py
keepluggable/orchestrator.py
keepluggable/storage_file/__init__.py
keepluggable/storage_file/amazon_s3.py
keepluggable/storage_file/local.py
keepluggable/storage_metadata/__init__.py
keepluggable/storage_metadata/sql.py
keepluggable/web/__init__.py
keepluggable/web/pyramid/__init__.py
keepluggable/web/pyramid/resources.py
keepluggable/web/pyramid/views.py
keepluggable-0.11.1.dist-info/WHEEL
keepluggable-0.11.1.dist-info/METADATA
keepluggable-0.11.1.dist-info/RECORD
